odoo/addons/crm_metadata/__init__.py
odoo/addons/crm_metadata/__manifest__.py
odoo/addons/crm_metadata/models/__init__.py
odoo/addons/crm_metadata/models/crm_lead.py
odoo/addons/crm_metadata/models/crm_lead_metadata_line.py
odoo/addons/crm_metadata/security/ir.model.access.csv
odoo/addons/crm_metadata/views/crm_lead.xml
odoo12_addon_crm_metadata-12.0.0.0.1.dist-info/METADATA
odoo12_addon_crm_metadata-12.0.0.0.1.dist-info/WHEEL
odoo12_addon_crm_metadata-12.0.0.0.1.dist-info/top_level.txt
odoo12_addon_crm_metadata-12.0.0.0.1.dist-info/RECORD
