Metadata-Version: 2.1
Name: odoo12-addon-crm-metadata
Version: 12.0.0.0.1
Summary: Add metadata to crm lead
Home-page: 
Author: Coopdevs Treball SCCL
Classifier: Programming Language :: Python
Classifier: Framework :: Odoo
Classifier: Framework :: Odoo :: 12.0
Requires-Python: >=3.5
Requires-Dist: odoo12-addon-metadata
Requires-Dist: odoo (<12.1dev,>=12.0a)
